{
  "template_version": "2.0",
  "report": {
    "report_date": "2026-05-13",
    "display_date": "2026년 5월 13일 (수)",
    "previous_day_label": "5/12",
    "today_label": "5/13",
    "generated_at": "2026-05-28 01:51 KST",
    "review_status": "초안",
    "report_version": "draft-from-safetimes-v2.0",
    "header_title": "Daily Issue Report",
    "report_title": "Daily Issue Report",
    "report_badge": "정유 · 석유화학 · LNG",
    "meta_description": "정유·석유화학·LNG 관련 일일 유가 동향 및 주요 이슈 리포트",
    "previous_source_date": "2026-05-12"
  },
  "summary": [
    {
      "type": "stakeholder",
      "text": "주요 이해관계자 동향: 5/12 기준 08:00 중동전쟁 대응 보건의약단체 회의(서울), 정무위원회 법안심사제1소위원회(10:00 본관 604호), 제21회 국무회의 겸 제8차 비상경제점검회의(10:00 청와대)."
    },
    {
      "type": "today",
      "text": "금일 주요 일정: 07:45 ESS 생산 및 실증 현장방문(계룡·대전), 08:00 비상경제본부회의, 08:30 비상경제본부회의 참석(서울), 08:30 비상경제본부회의(국무총리실)."
    },
    {
      "type": "news_trend",
      "text": "조간 보도: 주요 매체가 △석유 최고가격제·유류세 등 가격 안정 정책 △중동 정세와 원유·LNG 수급 리스크 △정유·석유화학 업계 실적·원가·제품 가격 △물가 지표와 에너지 비용 부담 등을 중심으로 보도."
    }
  ],
  "prices": {
    "unit": "$/Bbl",
    "price_data_note": "※ 오피넷 기준. 과거 2개월만 표시, 값이 0인 가격은 제외.",
    "crude": {
      "base_label": "5/12",
      "cards": [
        {
          "label": "Brent",
          "value": 107.77,
          "change": 3.56,
          "direction": "up",
          "unit": "$/Bbl"
        },
        {
          "label": "WTI",
          "value": 102.18,
          "change": 4.11,
          "direction": "up",
          "unit": "$/Bbl"
        },
        {
          "label": "Dubai",
          "value": 104.9,
          "change": 3.79,
          "direction": "up",
          "unit": "$/Bbl"
        }
      ],
      "chart_period_label": "3/12~5/12",
      "chart_window": {
        "start": "2026-03-12",
        "end": "2026-05-12",
        "rule": "report_date - 1 day, then minus 2 calendar months"
      },
      "chart_series": {
        "Brent": [
          {
            "date": "2026-03-12",
            "label": "3/12",
            "value": 100.46
          },
          {
            "date": "2026-03-13",
            "label": "3/13",
            "value": 103.14
          },
          {
            "date": "2026-03-16",
            "label": "3/16",
            "value": 100.21
          },
          {
            "date": "2026-03-17",
            "label": "3/17",
            "value": 103.42
          },
          {
            "date": "2026-03-18",
            "label": "3/18",
            "value": 107.38
          },
          {
            "date": "2026-03-19",
            "label": "3/19",
            "value": 108.65
          },
          {
            "date": "2026-03-20",
            "label": "3/20",
            "value": 112.19
          },
          {
            "date": "2026-03-23",
            "label": "3/23",
            "value": 99.94
          },
          {
            "date": "2026-03-24",
            "label": "3/24",
            "value": 104.49
          },
          {
            "date": "2026-03-25",
            "label": "3/25",
            "value": 102.22
          },
          {
            "date": "2026-03-26",
            "label": "3/26",
            "value": 108.01
          },
          {
            "date": "2026-03-27",
            "label": "3/27",
            "value": 112.57
          },
          {
            "date": "2026-03-30",
            "label": "3/30",
            "value": 112.78
          },
          {
            "date": "2026-03-31",
            "label": "3/31",
            "value": 118.35
          },
          {
            "date": "2026-04-01",
            "label": "4/1",
            "value": 101.16
          },
          {
            "date": "2026-04-02",
            "label": "4/2",
            "value": 109.03
          },
          {
            "date": "2026-04-06",
            "label": "4/6",
            "value": 109.77
          },
          {
            "date": "2026-04-07",
            "label": "4/7",
            "value": 109.27
          },
          {
            "date": "2026-04-08",
            "label": "4/8",
            "value": 94.75
          },
          {
            "date": "2026-04-09",
            "label": "4/9",
            "value": 95.92
          },
          {
            "date": "2026-04-10",
            "label": "4/10",
            "value": 95.2
          },
          {
            "date": "2026-04-13",
            "label": "4/13",
            "value": 99.36
          },
          {
            "date": "2026-04-14",
            "label": "4/14",
            "value": 94.79
          },
          {
            "date": "2026-04-15",
            "label": "4/15",
            "value": 94.93
          },
          {
            "date": "2026-04-16",
            "label": "4/16",
            "value": 99.39
          },
          {
            "date": "2026-04-17",
            "label": "4/17",
            "value": 90.38
          },
          {
            "date": "2026-04-20",
            "label": "4/20",
            "value": 95.48
          },
          {
            "date": "2026-04-21",
            "label": "4/21",
            "value": 98.48
          },
          {
            "date": "2026-04-22",
            "label": "4/22",
            "value": 101.91
          },
          {
            "date": "2026-04-23",
            "label": "4/23",
            "value": 105.07
          },
          {
            "date": "2026-04-24",
            "label": "4/24",
            "value": 105.33
          },
          {
            "date": "2026-04-27",
            "label": "4/27",
            "value": 108.23
          },
          {
            "date": "2026-04-28",
            "label": "4/28",
            "value": 111.26
          },
          {
            "date": "2026-04-29",
            "label": "4/29",
            "value": 118.03
          },
          {
            "date": "2026-04-30",
            "label": "4/30",
            "value": 114.01
          },
          {
            "date": "2026-05-01",
            "label": "5/1",
            "value": 108.17
          },
          {
            "date": "2026-05-04",
            "label": "5/4",
            "value": 114.44
          },
          {
            "date": "2026-05-05",
            "label": "5/5",
            "value": 109.87
          },
          {
            "date": "2026-05-06",
            "label": "5/6",
            "value": 101.27
          },
          {
            "date": "2026-05-07",
            "label": "5/7",
            "value": 100.06
          },
          {
            "date": "2026-05-08",
            "label": "5/8",
            "value": 101.29
          },
          {
            "date": "2026-05-11",
            "label": "5/11",
            "value": 104.21
          },
          {
            "date": "2026-05-12",
            "label": "5/12",
            "value": 107.77
          }
        ],
        "WTI": [
          {
            "date": "2026-03-12",
            "label": "3/12",
            "value": 95.73
          },
          {
            "date": "2026-03-13",
            "label": "3/13",
            "value": 98.71
          },
          {
            "date": "2026-03-16",
            "label": "3/16",
            "value": 93.5
          },
          {
            "date": "2026-03-17",
            "label": "3/17",
            "value": 96.21
          },
          {
            "date": "2026-03-18",
            "label": "3/18",
            "value": 96.32
          },
          {
            "date": "2026-03-19",
            "label": "3/19",
            "value": 96.14
          },
          {
            "date": "2026-03-20",
            "label": "3/20",
            "value": 98.32
          },
          {
            "date": "2026-03-23",
            "label": "3/23",
            "value": 88.13
          },
          {
            "date": "2026-03-24",
            "label": "3/24",
            "value": 92.35
          },
          {
            "date": "2026-03-25",
            "label": "3/25",
            "value": 90.32
          },
          {
            "date": "2026-03-26",
            "label": "3/26",
            "value": 94.48
          },
          {
            "date": "2026-03-27",
            "label": "3/27",
            "value": 99.64
          },
          {
            "date": "2026-03-30",
            "label": "3/30",
            "value": 102.88
          },
          {
            "date": "2026-03-31",
            "label": "3/31",
            "value": 101.38
          },
          {
            "date": "2026-04-01",
            "label": "4/1",
            "value": 100.12
          },
          {
            "date": "2026-04-02",
            "label": "4/2",
            "value": 111.54
          },
          {
            "date": "2026-04-06",
            "label": "4/6",
            "value": 112.41
          },
          {
            "date": "2026-04-07",
            "label": "4/7",
            "value": 112.95
          },
          {
            "date": "2026-04-08",
            "label": "4/8",
            "value": 94.41
          },
          {
            "date": "2026-04-09",
            "label": "4/9",
            "value": 97.87
          },
          {
            "date": "2026-04-10",
            "label": "4/10",
            "value": 96.57
          },
          {
            "date": "2026-04-13",
            "label": "4/13",
            "value": 99.08
          },
          {
            "date": "2026-04-14",
            "label": "4/14",
            "value": 91.28
          },
          {
            "date": "2026-04-15",
            "label": "4/15",
            "value": 91.29
          },
          {
            "date": "2026-04-16",
            "label": "4/16",
            "value": 94.69
          },
          {
            "date": "2026-04-17",
            "label": "4/17",
            "value": 83.85
          },
          {
            "date": "2026-04-20",
            "label": "4/20",
            "value": 89.61
          },
          {
            "date": "2026-04-21",
            "label": "4/21",
            "value": 92.13
          },
          {
            "date": "2026-04-22",
            "label": "4/22",
            "value": 92.96
          },
          {
            "date": "2026-04-23",
            "label": "4/23",
            "value": 95.85
          },
          {
            "date": "2026-04-24",
            "label": "4/24",
            "value": 94.4
          },
          {
            "date": "2026-04-27",
            "label": "4/27",
            "value": 96.37
          },
          {
            "date": "2026-04-28",
            "label": "4/28",
            "value": 99.93
          },
          {
            "date": "2026-04-29",
            "label": "4/29",
            "value": 106.88
          },
          {
            "date": "2026-04-30",
            "label": "4/30",
            "value": 105.07
          },
          {
            "date": "2026-05-01",
            "label": "5/1",
            "value": 101.94
          },
          {
            "date": "2026-05-04",
            "label": "5/4",
            "value": 106.42
          },
          {
            "date": "2026-05-05",
            "label": "5/5",
            "value": 102.27
          },
          {
            "date": "2026-05-06",
            "label": "5/6",
            "value": 95.08
          },
          {
            "date": "2026-05-07",
            "label": "5/7",
            "value": 94.81
          },
          {
            "date": "2026-05-08",
            "label": "5/8",
            "value": 95.42
          },
          {
            "date": "2026-05-11",
            "label": "5/11",
            "value": 98.07
          },
          {
            "date": "2026-05-12",
            "label": "5/12",
            "value": 102.18
          }
        ],
        "Dubai": [
          {
            "date": "2026-03-12",
            "label": "3/12",
            "value": 134.4
          },
          {
            "date": "2026-03-13",
            "label": "3/13",
            "value": 145.51
          },
          {
            "date": "2026-03-16",
            "label": "3/16",
            "value": 153.24
          },
          {
            "date": "2026-03-17",
            "label": "3/17",
            "value": 157.66
          },
          {
            "date": "2026-03-18",
            "label": "3/18",
            "value": 155.55
          },
          {
            "date": "2026-03-19",
            "label": "3/19",
            "value": 166.8
          },
          {
            "date": "2026-03-20",
            "label": "3/20",
            "value": 158.85
          },
          {
            "date": "2026-03-23",
            "label": "3/23",
            "value": 169.75
          },
          {
            "date": "2026-03-24",
            "label": "3/24",
            "value": 157.03
          },
          {
            "date": "2026-03-25",
            "label": "3/25",
            "value": 142.55
          },
          {
            "date": "2026-03-26",
            "label": "3/26",
            "value": 113.04
          },
          {
            "date": "2026-03-27",
            "label": "3/27",
            "value": 122.14
          },
          {
            "date": "2026-03-30",
            "label": "3/30",
            "value": 125.29
          },
          {
            "date": "2026-03-31",
            "label": "3/31",
            "value": 121.1
          },
          {
            "date": "2026-04-01",
            "label": "4/1",
            "value": 108.9
          },
          {
            "date": "2026-04-02",
            "label": "4/2",
            "value": 114.6
          },
          {
            "date": "2026-04-06",
            "label": "4/6",
            "value": 120.2
          },
          {
            "date": "2026-04-07",
            "label": "4/7",
            "value": 121.86
          },
          {
            "date": "2026-04-08",
            "label": "4/8",
            "value": 101.2
          },
          {
            "date": "2026-04-09",
            "label": "4/9",
            "value": 102.0
          },
          {
            "date": "2026-04-10",
            "label": "4/10",
            "value": 100.87
          },
          {
            "date": "2026-04-13",
            "label": "4/13",
            "value": 106.5
          },
          {
            "date": "2026-04-14",
            "label": "4/14",
            "value": 103.18
          },
          {
            "date": "2026-04-15",
            "label": "4/15",
            "value": 101.09
          },
          {
            "date": "2026-04-16",
            "label": "4/16",
            "value": 101.8
          },
          {
            "date": "2026-04-17",
            "label": "4/17",
            "value": 102.2
          },
          {
            "date": "2026-04-20",
            "label": "4/20",
            "value": 98.5
          },
          {
            "date": "2026-04-21",
            "label": "4/21",
            "value": 94.27
          },
          {
            "date": "2026-04-22",
            "label": "4/22",
            "value": 100.4
          },
          {
            "date": "2026-04-23",
            "label": "4/23",
            "value": 104.81
          },
          {
            "date": "2026-04-24",
            "label": "4/24",
            "value": 107.2
          },
          {
            "date": "2026-04-27",
            "label": "4/27",
            "value": 104.2
          },
          {
            "date": "2026-04-28",
            "label": "4/28",
            "value": 107.2
          },
          {
            "date": "2026-04-29",
            "label": "4/29",
            "value": 106.49
          },
          {
            "date": "2026-04-30",
            "label": "4/30",
            "value": 112.2
          },
          {
            "date": "2026-05-04",
            "label": "5/4",
            "value": 102.84
          },
          {
            "date": "2026-05-05",
            "label": "5/5",
            "value": 106.6
          },
          {
            "date": "2026-05-06",
            "label": "5/6",
            "value": 103.69
          },
          {
            "date": "2026-05-07",
            "label": "5/7",
            "value": 97.59
          },
          {
            "date": "2026-05-08",
            "label": "5/8",
            "value": 97.39
          },
          {
            "date": "2026-05-11",
            "label": "5/11",
            "value": 101.11
          },
          {
            "date": "2026-05-12",
            "label": "5/12",
            "value": 104.9
          }
        ]
      }
    },
    "products": {
      "base_label": "5/12",
      "cards": [
        {
          "label": "휘발유",
          "value": 132.42,
          "change": 5.0,
          "direction": "up",
          "unit": "$/Bbl"
        },
        {
          "label": "경유",
          "value": 160.25,
          "change": 4.92,
          "direction": "up",
          "unit": "$/Bbl"
        },
        {
          "label": "나프타",
          "value": 113.64,
          "change": 4.11,
          "direction": "up",
          "unit": "$/Bbl"
        }
      ],
      "chart_period_label": "3/12~5/12",
      "chart_window": {
        "start": "2026-03-12",
        "end": "2026-05-12",
        "rule": "report_date - 1 day, then minus 2 calendar months"
      },
      "chart_series": {
        "Gasoline": [
          {
            "date": "2026-03-12",
            "label": "3/12",
            "value": 130.12
          },
          {
            "date": "2026-03-13",
            "label": "3/13",
            "value": 136.44
          },
          {
            "date": "2026-03-16",
            "label": "3/16",
            "value": 140.16
          },
          {
            "date": "2026-03-17",
            "label": "3/17",
            "value": 138.84
          },
          {
            "date": "2026-03-18",
            "label": "3/18",
            "value": 139.78
          },
          {
            "date": "2026-03-19",
            "label": "3/19",
            "value": 151.92
          },
          {
            "date": "2026-03-20",
            "label": "3/20",
            "value": 150.6
          },
          {
            "date": "2026-03-23",
            "label": "3/23",
            "value": 157.22
          },
          {
            "date": "2026-03-24",
            "label": "3/24",
            "value": 141.76
          },
          {
            "date": "2026-03-25",
            "label": "3/25",
            "value": 131.0
          },
          {
            "date": "2026-03-26",
            "label": "3/26",
            "value": 127.48
          },
          {
            "date": "2026-03-27",
            "label": "3/27",
            "value": 130.51
          },
          {
            "date": "2026-03-30",
            "label": "3/30",
            "value": 139.65
          },
          {
            "date": "2026-03-31",
            "label": "3/31",
            "value": 138.45
          },
          {
            "date": "2026-04-01",
            "label": "4/1",
            "value": 136.03
          },
          {
            "date": "2026-04-02",
            "label": "4/2",
            "value": 144.48
          },
          {
            "date": "2026-04-06",
            "label": "4/6",
            "value": 141.88
          },
          {
            "date": "2026-04-07",
            "label": "4/7",
            "value": 138.22
          },
          {
            "date": "2026-04-08",
            "label": "4/8",
            "value": 119.48
          },
          {
            "date": "2026-04-09",
            "label": "4/9",
            "value": 130.98
          },
          {
            "date": "2026-04-10",
            "label": "4/10",
            "value": 128.19
          },
          {
            "date": "2026-04-13",
            "label": "4/13",
            "value": 128.48
          },
          {
            "date": "2026-04-14",
            "label": "4/14",
            "value": 123.87
          },
          {
            "date": "2026-04-15",
            "label": "4/15",
            "value": 119.0
          },
          {
            "date": "2026-04-16",
            "label": "4/16",
            "value": 120.86
          },
          {
            "date": "2026-04-17",
            "label": "4/17",
            "value": 122.19
          },
          {
            "date": "2026-04-20",
            "label": "4/20",
            "value": 118.68
          },
          {
            "date": "2026-04-21",
            "label": "4/21",
            "value": 118.21
          },
          {
            "date": "2026-04-22",
            "label": "4/22",
            "value": 124.25
          },
          {
            "date": "2026-04-23",
            "label": "4/23",
            "value": 125.92
          },
          {
            "date": "2026-04-24",
            "label": "4/24",
            "value": 124.68
          },
          {
            "date": "2026-04-27",
            "label": "4/27",
            "value": 128.04
          },
          {
            "date": "2026-04-28",
            "label": "4/28",
            "value": 126.52
          },
          {
            "date": "2026-04-29",
            "label": "4/29",
            "value": 129.83
          },
          {
            "date": "2026-04-30",
            "label": "4/30",
            "value": 134.29
          },
          {
            "date": "2026-05-04",
            "label": "5/4",
            "value": 130.9
          },
          {
            "date": "2026-05-05",
            "label": "5/5",
            "value": 136.61
          },
          {
            "date": "2026-05-06",
            "label": "5/6",
            "value": 133.35
          },
          {
            "date": "2026-05-07",
            "label": "5/7",
            "value": 126.12
          },
          {
            "date": "2026-05-08",
            "label": "5/8",
            "value": 123.01
          },
          {
            "date": "2026-05-11",
            "label": "5/11",
            "value": 127.42
          },
          {
            "date": "2026-05-12",
            "label": "5/12",
            "value": 132.42
          }
        ],
        "Diesel": [
          {
            "date": "2026-03-12",
            "label": "3/12",
            "value": 194.5
          },
          {
            "date": "2026-03-13",
            "label": "3/13",
            "value": 192.48
          },
          {
            "date": "2026-03-16",
            "label": "3/16",
            "value": 190.93
          },
          {
            "date": "2026-03-17",
            "label": "3/17",
            "value": 198.2
          },
          {
            "date": "2026-03-18",
            "label": "3/18",
            "value": 198.87
          },
          {
            "date": "2026-03-19",
            "label": "3/19",
            "value": 224.49
          },
          {
            "date": "2026-03-20",
            "label": "3/20",
            "value": 222.99
          },
          {
            "date": "2026-03-23",
            "label": "3/23",
            "value": 242.89
          },
          {
            "date": "2026-03-24",
            "label": "3/24",
            "value": 219.9
          },
          {
            "date": "2026-03-25",
            "label": "3/25",
            "value": 205.54
          },
          {
            "date": "2026-03-26",
            "label": "3/26",
            "value": 216.56
          },
          {
            "date": "2026-03-27",
            "label": "3/27",
            "value": 237.83
          },
          {
            "date": "2026-03-30",
            "label": "3/30",
            "value": 252.14
          },
          {
            "date": "2026-03-31",
            "label": "3/31",
            "value": 238.88
          },
          {
            "date": "2026-04-01",
            "label": "4/1",
            "value": 245.99
          },
          {
            "date": "2026-04-02",
            "label": "4/2",
            "value": 292.8
          },
          {
            "date": "2026-04-06",
            "label": "4/6",
            "value": 272.65
          },
          {
            "date": "2026-04-07",
            "label": "4/7",
            "value": 255.33
          },
          {
            "date": "2026-04-08",
            "label": "4/8",
            "value": 198.37
          },
          {
            "date": "2026-04-09",
            "label": "4/9",
            "value": 210.99
          },
          {
            "date": "2026-04-10",
            "label": "4/10",
            "value": 210.13
          },
          {
            "date": "2026-04-13",
            "label": "4/13",
            "value": 203.21
          },
          {
            "date": "2026-04-14",
            "label": "4/14",
            "value": 191.74
          },
          {
            "date": "2026-04-15",
            "label": "4/15",
            "value": 173.32
          },
          {
            "date": "2026-04-16",
            "label": "4/16",
            "value": 172.23
          },
          {
            "date": "2026-04-17",
            "label": "4/17",
            "value": 170.31
          },
          {
            "date": "2026-04-20",
            "label": "4/20",
            "value": 155.07
          },
          {
            "date": "2026-04-21",
            "label": "4/21",
            "value": 152.84
          },
          {
            "date": "2026-04-22",
            "label": "4/22",
            "value": 167.2
          },
          {
            "date": "2026-04-23",
            "label": "4/23",
            "value": 171.26
          },
          {
            "date": "2026-04-24",
            "label": "4/24",
            "value": 172.84
          },
          {
            "date": "2026-04-27",
            "label": "4/27",
            "value": 174.04
          },
          {
            "date": "2026-04-28",
            "label": "4/28",
            "value": 167.38
          },
          {
            "date": "2026-04-29",
            "label": "4/29",
            "value": 169.49
          },
          {
            "date": "2026-04-30",
            "label": "4/30",
            "value": 178.67
          },
          {
            "date": "2026-05-04",
            "label": "5/4",
            "value": 160.73
          },
          {
            "date": "2026-05-05",
            "label": "5/5",
            "value": 160.96
          },
          {
            "date": "2026-05-06",
            "label": "5/6",
            "value": 157.05
          },
          {
            "date": "2026-05-07",
            "label": "5/7",
            "value": 149.29
          },
          {
            "date": "2026-05-08",
            "label": "5/8",
            "value": 153.49
          },
          {
            "date": "2026-05-11",
            "label": "5/11",
            "value": 155.33
          },
          {
            "date": "2026-05-12",
            "label": "5/12",
            "value": 160.25
          }
        ],
        "Naphtha": [
          {
            "date": "2026-03-12",
            "label": "3/12",
            "value": 113.3
          },
          {
            "date": "2026-03-13",
            "label": "3/13",
            "value": 122.46
          },
          {
            "date": "2026-03-16",
            "label": "3/16",
            "value": 127.95
          },
          {
            "date": "2026-03-17",
            "label": "3/17",
            "value": 124.53
          },
          {
            "date": "2026-03-18",
            "label": "3/18",
            "value": 124.44
          },
          {
            "date": "2026-03-19",
            "label": "3/19",
            "value": 137.72
          },
          {
            "date": "2026-03-20",
            "label": "3/20",
            "value": 133.97
          },
          {
            "date": "2026-03-23",
            "label": "3/23",
            "value": 138.75
          },
          {
            "date": "2026-03-24",
            "label": "3/24",
            "value": 127.52
          },
          {
            "date": "2026-03-25",
            "label": "3/25",
            "value": 117.62
          },
          {
            "date": "2026-03-26",
            "label": "3/26",
            "value": 129.12
          },
          {
            "date": "2026-03-27",
            "label": "3/27",
            "value": 133.74
          },
          {
            "date": "2026-03-30",
            "label": "3/30",
            "value": 141.53
          },
          {
            "date": "2026-03-31",
            "label": "3/31",
            "value": 141.72
          },
          {
            "date": "2026-04-01",
            "label": "4/1",
            "value": 136.69
          },
          {
            "date": "2026-04-02",
            "label": "4/2",
            "value": 141.26
          },
          {
            "date": "2026-04-06",
            "label": "4/6",
            "value": 137.08
          },
          {
            "date": "2026-04-07",
            "label": "4/7",
            "value": 137.24
          },
          {
            "date": "2026-04-08",
            "label": "4/8",
            "value": 118.46
          },
          {
            "date": "2026-04-09",
            "label": "4/9",
            "value": 124.14
          },
          {
            "date": "2026-04-10",
            "label": "4/10",
            "value": 123.14
          },
          {
            "date": "2026-04-13",
            "label": "4/13",
            "value": 126.04
          },
          {
            "date": "2026-04-14",
            "label": "4/14",
            "value": 121.59
          },
          {
            "date": "2026-04-15",
            "label": "4/15",
            "value": 116.14
          },
          {
            "date": "2026-04-16",
            "label": "4/16",
            "value": 115.88
          },
          {
            "date": "2026-04-17",
            "label": "4/17",
            "value": 115.6
          },
          {
            "date": "2026-04-20",
            "label": "4/20",
            "value": 106.04
          },
          {
            "date": "2026-04-21",
            "label": "4/21",
            "value": 103.99
          },
          {
            "date": "2026-04-22",
            "label": "4/22",
            "value": 110.61
          },
          {
            "date": "2026-04-23",
            "label": "4/23",
            "value": 114.9
          },
          {
            "date": "2026-04-24",
            "label": "4/24",
            "value": 118.3
          },
          {
            "date": "2026-04-27",
            "label": "4/27",
            "value": 119.67
          },
          {
            "date": "2026-04-28",
            "label": "4/28",
            "value": 117.94
          },
          {
            "date": "2026-04-29",
            "label": "4/29",
            "value": 120.3
          },
          {
            "date": "2026-04-30",
            "label": "4/30",
            "value": 128.56
          },
          {
            "date": "2026-05-04",
            "label": "5/4",
            "value": 117.57
          },
          {
            "date": "2026-05-05",
            "label": "5/5",
            "value": 117.79
          },
          {
            "date": "2026-05-06",
            "label": "5/6",
            "value": 108.7
          },
          {
            "date": "2026-05-07",
            "label": "5/7",
            "value": 101.97
          },
          {
            "date": "2026-05-08",
            "label": "5/8",
            "value": 102.45
          },
          {
            "date": "2026-05-11",
            "label": "5/11",
            "value": 109.53
          },
          {
            "date": "2026-05-12",
            "label": "5/12",
            "value": 113.64
          }
        ]
      }
    }
  },
  "issues": [
    {
      "category": "정책",
      "category_class": "",
      "title": "중동전쟁 대응 보건의약단체 회의",
      "description": "08:00 · 이형훈 2차관 · 서울",
      "time": "08:00",
      "org": "이형훈 2차관",
      "location": "서울",
      "links": [
        {
          "label": "관련 기사 없음",
          "url": ""
        }
      ],
      "grade": "",
      "grade_class": ""
    },
    {
      "category": "국회",
      "category_class": "",
      "title": "정무위원회 법안심사제1소위원회",
      "description": "10:00 · 국회 · 본관 604호",
      "time": "10:00",
      "org": "국회",
      "location": "본관 604호",
      "links": [
        {
          "label": "관련 기사 없음",
          "url": ""
        }
      ],
      "grade": "",
      "grade_class": ""
    },
    {
      "category": "정책",
      "category_class": "",
      "title": "제21회 국무회의 겸 제8차 비상경제점검회의",
      "description": "10:00 · 대통령 · 청와대",
      "time": "10:00",
      "org": "대통령",
      "location": "청와대",
      "links": [
        {
          "label": "관련 기사 없음",
          "url": ""
        }
      ],
      "grade": "",
      "grade_class": ""
    },
    {
      "category": "정책",
      "category_class": "",
      "title": "중동전쟁 관련 수출기업 현장 방문",
      "description": "14:30 · 노용석 1차관 · 페스웰",
      "time": "14:30",
      "org": "노용석 1차관",
      "location": "페스웰",
      "links": [
        {
          "label": "관련 기사 없음",
          "url": ""
        }
      ],
      "grade": "",
      "grade_class": ""
    },
    {
      "category": "정책",
      "category_class": "",
      "title": "국채시장 자문위원회 정례회의",
      "description": "15:00 · 재경부",
      "time": "15:00",
      "org": "재경부",
      "location": "",
      "links": [
        {
          "label": "관련 기사 없음",
          "url": ""
        }
      ],
      "grade": "",
      "grade_class": ""
    },
    {
      "category": "에너지",
      "category_class": "",
      "title": "과기정통부-기후부 MOU",
      "description": "15:30 · 배경훈 부총리 겸 과기정통 · 정부서울청사",
      "time": "15:30",
      "org": "배경훈 부총리 겸 과기정통",
      "location": "정부서울청사",
      "links": [
        {
          "label": "관련 기사 없음",
          "url": ""
        }
      ],
      "grade": "",
      "grade_class": ""
    }
  ],
  "schedules": [
    {
      "time": "07:45",
      "org": "김성환 장관",
      "title": "07:45 ESS 생산 및 실증 현장방문(계룡·대전)",
      "relevance": ""
    },
    {
      "time": "08:00",
      "org": "기획처",
      "title": "08:00 비상경제본부회의",
      "relevance": ""
    },
    {
      "time": "08:30",
      "org": "김민재 차관",
      "title": "08:30 비상경제본부회의 참석(서울)",
      "relevance": ""
    },
    {
      "time": "08:30",
      "org": "조현 장관",
      "title": "08:30 비상경제본부회의(국무총리실)",
      "relevance": ""
    },
    {
      "time": "08:30",
      "org": "공정위 주병기 위원장",
      "title": "08:30 비상경제본부회의(세종청사)",
      "relevance": ""
    },
    {
      "time": "08:30",
      "org": "이형일 1차관",
      "title": "08:30 비상경제본부회의(정부서울청사)",
      "relevance": ""
    },
    {
      "time": "08:30",
      "org": "권창준 차관",
      "title": "08:30 제14차 비상경제본부 회의(정부서울청사)",
      "relevance": ""
    },
    {
      "time": "08:30",
      "org": "국무총리",
      "title": "비상경제본부회의(08:30 정부서울청사)",
      "relevance": ""
    },
    {
      "time": "09:40",
      "org": "공정위 주병기 위원장",
      "title": "09:40 현안점검 간부회의(대회의실)",
      "relevance": ""
    },
    {
      "time": "14:00",
      "org": "의원실 세미나",
      "title": "윤준병 의원실 등, 글로벌 에너지 공급망 위기와 한-러 북극항로 협력(14:00 의원회관 제11간담회의실)",
      "relevance": ""
    },
    {
      "time": "15:00",
      "org": "송미령 장관",
      "title": "15:00 농업·농촌 에너지 대전환 선도지역 현장간담회(강원 춘천)",
      "relevance": ""
    }
  ],
  "news_trend": {
    "summary": "주요 매체가 △석유 최고가격제·유류세 등 가격 안정 정책 △중동 정세와 원유·LNG 수급 리스크 △정유·석유화학 업계 실적·원가·제품 가격 △물가 지표와 에너지 비용 부담 등을 중심으로 보도.",
    "trend_paragraphs": [
      "Chosunbiz는 5/12 16:00 입력 기사에서 정유업계 수익성·원가·시장 여건 변화를 중심으로 보도.",
      "물류신문은 5/12 17:15 입력 기사에서 석유화학 업황과 주요 기업·시장 변수 관련 쟁점 정리.",
      "조선일보는 5/12 16:00 입력 기사에서 석유화학 업황과 주요 기업·시장 변수 관련 쟁점 정리."
    ],
    "articles": [
      {
        "title": "[단독] 석유公 해외 자회사·지분 투자 광구서 생산한 원유 들어온다… 다음 달부터 정유사 판매 - 조선비즈 - Chosunbiz",
        "press": "Chosunbiz",
        "url": "https://news.google.com/rss/articles/CBMihAFBVV95cUxNUmhVeE0zVkM1djd3bWlLbUY5blZEVlJ1M3ZWek1pZWZxb3JpR09IV3pCcmJJbTVBMWVyWXd6Z2YyclR1RnJWMVZGajdzbk5CTTlJd1lCb3pXTkY3UWo3eXpKLXZUTTdvSTM4bUxoX1l2X2pBSkNzZmtmZ0sycTNlWXd5SVfSAZgBQVVfeXFMTmFHN3VBMGxVNHAzTGsxNkdpZkxsQzdsUEF1Um0wZngzQkpULWxqaEdVajFZMG9RSko4cTY0U0tLdE9kT25xRzFxdzVIVGxHTTVmQk1qWDFFRVExSkExR3dnbnZNVWlRTlBjZHdEVG1famg2d3FBdmlYNGszZ21HSnZxU19pMmFvM2JjM2N5b2FFQVBGQlN1bHk?oc=5",
        "summary": "정유업계 수익성·원가·시장 여건 변화를 중심으로 보도",
        "published_at_kst": "2026-05-12 16:00"
      },
      {
        "title": "관세청, “호르무즈 우회한 석유화학 원료 수급 적극 지원” - 물류신문",
        "press": "물류신문",
        "url": "https://news.google.com/rss/articles/CBMia0FVX3lxTE1Oekdvc281V240R3BKZGhqazhFQ3NmY1dfbjVweUZaaGVnRVJ6NFM1UVVabHRFQlpIVXVHcTZTMFlYN1E2eHIzZWxXRVNjeVNwOUNKRG8zMDZ4bHI3VHJJOHR6TWllNFdtZF84?oc=5",
        "summary": "석유화학 업황과 주요 기업·시장 변수 관련 쟁점 정리",
        "published_at_kst": "2026-05-12 17:15"
      },
      {
        "title": "나프타 수급 차질에도 석유화학 1분기 깜짝 실적 - 조선일보",
        "press": "조선일보",
        "url": "https://news.google.com/rss/articles/CBMijwFBVV95cUxNdHgxTkRyV2JMUjNtZHBBM3FmeExiMl8xS01MeFd6OUxKcHZWYmdiVHQ2QjdjQmFaSlVOMFBSSERFUEdnMFRXSlVSTHNlcmpWMTlXSUtGQjAwTlZQWGR6QUtreDdxcmkyM0FENmJPckNJX3ZYSllBOEEwZUNxbmF3ZHlVSmFKMVRUVEZHMHAwTQ?oc=5",
        "summary": "석유화학 업황과 주요 기업·시장 변수 관련 쟁점 정리",
        "published_at_kst": "2026-05-12 16:00"
      }
    ],
    "source": "Google News RSS",
    "needs_review": true
  },
  "quality_control": {
    "quality_notes": [
      "기사 제목·URL·발행일 확인 후 대표 기사로 사용합니다.",
      "일정·보도자료 원문 확인 범위 내에서 작성합니다.",
      "가격 데이터에서 0값은 카드·그래프 산출에서 제외합니다.",
      "정책 방향, 정부 의도, 업계 손익 영향은 원문 근거가 없는 경우 단정하지 않습니다.",
      "일정은 자동 추출 결과이므로 시간·기관·일정명 확인 필요.",
      "가격 추이 그래프는 기준일 전일 기준 과거 2개월(3/12~5/12)만 표시하며, 전체 장기 데이터는 history.json에 보유합니다.",
      "값이 0인 가격은 그래프 이력에서 제외했습니다.",
      "과거 날짜에 일별 가격 JSON이 없더라도 history.json에서 가격 카드와 그래프를 생성합니다."
    ],
    "sources": [
      {
        "name": "오늘의 주요일정",
        "type": "schedule",
        "url": "https://www.safetimes.co.kr/news/articleView.html?idxno=242723"
      },
      {
        "name": "국제 원유가격 원천 데이터",
        "type": "price_file",
        "url": ""
      },
      {
        "name": "국제 석유제품가격 원천 데이터",
        "type": "price_file",
        "url": ""
      },
      {
        "name": "대표 기사 원문",
        "type": "news",
        "url": ""
      },
      {
        "name": "오피넷 국제유가 > 원유",
        "type": "price",
        "url": ""
      },
      {
        "name": "오피넷 국제유가 > 석유제품",
        "type": "price",
        "url": ""
      },
      {
        "name": "장기 가격 이력 history.json",
        "type": "price-history",
        "url": ""
      }
    ]
  },
  "footer": {
    "text": "SK Innovation Communication Division · 2026.05.20<br>Source: 사용자 제공 기본 데이터, 세이프타임즈 일정, 가격 원천자료, 대표 기사 원문"
  },
  "generator_rules": {
    "html_escape_required_fields": [
      "summary.text",
      "issues.description",
      "schedules.relevance",
      "news_trend.articles.title",
      "news_trend.articles.press"
    ],
    "html_allowed_fields": [
      "news_trend.summary_html",
      "footer.text"
    ],
    "exclude_price_value_if_zero": true,
    "news_article_count_target": 3,
    "summary_item_count_target": 3,
    "issue_count_range": [
      3,
      5
    ],
    "schedule_sort": "time_ascending",
    "chart_required_svg_elements": [
      "svg.price-chart-svg",
      "line.hover-line",
      "g.hover-dots",
      "rect.chart-hitbox"
    ]
  },
  "automation": {
    "safetimes": {
      "today_source_file_date": "2026-05-13",
      "today_source_title": "",
      "today_source_url": "https://www.safetimes.co.kr/news/articleView.html?idxno=242723",
      "today_source_published_at": "2026-05-13",
      "today_parsed_schedule_count": 11,
      "previous_source_file_date": "2026-05-12",
      "previous_source_title": "[오늘의 주요일정·12일] 이재명 대통령 비상경제점검회의",
      "previous_source_url": "https://www.safetimes.co.kr/news/articleView.html?idxno=242687",
      "previous_parsed_schedule_count": 10,
      "parser_version": "build_report_draft_from_schedule.py v2.1-prevday-separated",
      "needs_review": true
    },
    "news": {
      "source_file": "data/news/2026-05-13.json",
      "article_count": 3,
      "source": "Google News RSS",
      "status": "updated",
      "needs_review": true
    },
    "opinet_prices": {
      "price_json_used": false,
      "source_date": "",
      "history_schema_version": "1.3",
      "history_period": {
        "start": "2026-01-01",
        "end": "2026-05-20"
      },
      "chart_window": {
        "start": "2026-03-12",
        "end": "2026-05-12",
        "rule": "report_date - 1 day, then minus 2 calendar months"
      },
      "crude_chart_source": "history.json window",
      "products_chart_source": "history.json window",
      "merged_at": "2026-05-28 01:51:15 KST",
      "merge_script": "merge_prices_into_report.py v1.4",
      "needs_review": true
    }
  }
}