{
  "schema_version": "2.0",
  "source": "세이프타임즈",
  "category": "오늘의 주요일정",
  "date": "2026-07-03",
  "title": "",
  "article_title": "[오늘의 주요일정·3일] 한성숙 국무총리, 홍수 대응체계 현장점검",
  "article_url": "https://www.safetimes.co.kr/news/articleView.html?idxno=243923",
  "url": "https://www.safetimes.co.kr/news/articleView.html?idxno=243923",
  "approved_date": "2026-07-03",
  "collected_at": "2026-07-03 13:04:06 KST",
  "items": [
    {
      "text": "▲ 한성숙 국무총리, 홍수 대응체계 현장점검(11:00 서초구)"
    },
    {
      "text": ", 후반기 국회 대비 국회의원 워크숍(14:00 용산구)"
    },
    {
      "text": "▲ 조정식 국회의장, 정은경 보건복지부 장관 접견(14:00 의장 집무실)"
    },
    {
      "text": "▲ 국회 재정경제기획위원회 전체회의(11:00 본관 430호)"
    },
    {
      "text": "한병도 당대표 직무대행 및 원내대표, 최고위원회의(09:30 본관 당대표회의실)"
    },
    {
      "text": "한병도 당대표 직무대행 및 원내대표, 후반기 국회 대비 국회의원 워크숍(14:00 서울드래곤시티호텔)"
    },
    {
      "text": "정점식 원내대표, 원내대책회의(09:00 본관 245호)"
    },
    {
      "text": "신장식 당대표 권한대행, 소상공인연합회 정책간담회(10:00 소상공인연합회)"
    },
    {
      "text": "신장식 당대표 권한대행, 노회찬 8주기 추모 행사(14:00 국회의원회관 제3세미나실)"
    },
    {
      "text": "김준형 원내대표, 유튜브 <장르만 여의도> 출연(12:00)"
    },
    {
      "text": "다른 내일 아카데미 특강(19:00 부평아트센터)"
    },
    {
      "text": "이준석 대표, 메타콘 2026(10:00 코엑스 그랜드볼룸)"
    },
    {
      "text": "이준석 대표, 재정경제기획위원회 전체회의(11:00 본관 430호)"
    },
    {
      "text": "이준석 대표, 2026년 장애인 인권 증진 토론회(14:00 국회도서관 대강당)"
    },
    {
      "text": "▲ 보훈부, 당정협의(15:10 드래곤시티호텔)"
    },
    {
      "text": "▲ 금융위, 벤처생태계 간담회(09:10 부산 유라시아플랫폼)"
    },
    {
      "text": "▲ 금융위, 서민금융복합 지원센터 개소식(10:50 부산 서민금융 복합지원센터)"
    },
    {
      "text": "▲ 재경부, 비상경제본부 회의 겸 경제관계장관회의(08:30 정부세종청사)"
    },
    {
      "text": "▲ 기획처, 비상경제본부회의 겸 경제관계장관회의(08:30 정부서울청사)"
    },
    {
      "text": "▲ 산업부, 비상경제본부회의 겸 경제관계장관회의 개최계획(08:30 정부서울청사)"
    },
    {
      "text": "▲ 국토부, 집중호우 대비 현장점검(09:30 신탄진)"
    },
    {
      "text": "▲ 농식품부, 여름철 재해 대비 추진상황 점검회의 개최(09:00 세종)"
    },
    {
      "text": "▲ 농식품부, 국정과제 및 현안점검회의(10:00 세종)"
    },
    {
      "text": "▲ 중기부, 비상경제본부 회의(08:30 정부서울청사)"
    },
    {
      "text": "▲ 과기부, 글로벌AI 프론티어 심포지엄(09:30 웨스틴 서울 파르나스)"
    },
    {
      "text": "▲ 과기부, 성균관대 실험실창업 현장방문(10:00 수원 성균관대 창업보육센터)"
    },
    {
      "text": "▲ 과기부, 연구데이터 생산활용 현장방문(14:00 KIST)"
    },
    {
      "text": "▲ 오세훈 서울시장, 공항동 연합상권 민생현장방문(14:30 강서구 공항동 먹자골목 등)"
    },
    {
      "text": "▲ 행안부, 신선식품 배송서비스 출범식(13:20 경북 의성)"
    },
    {
      "text": "▲ 행안부, 지방소멸대응기금 현장방문(14:05 경북 의성)"
    },
    {
      "text": "▲ 행안부, 배송현장 사무소 및 마을 방문(14:30 경북 의성)"
    },
    {
      "text": "▲ 이정렬 개보위 부위원장, 개인정보 현장 컨설팅(14:00 대전정보문화산업진흥원)"
    },
    {
      "text": "▲ 성평등부, 경찰-가정폭력상담소 공동대응체계 현장간담회(14:00 정부서울청사)"
    },
    {
      "text": "▲ 복지부, 국립의학전문대학원 설립준비위원회(08:00 프레스센터)"
    },
    {
      "text": "▲ 노동부, 제조업 동일 유형 반복 산재 사고 예방 점검 회의(14:00 서울)"
    },
    {
      "text": "▲ 노동부, 제2차 고용노동부 양성평등위원회(15:00 서울)"
    },
    {
      "text": "▲ 기후부, 비닐봉투 없는 날 1회용품 감량 캠페인(10:00 서울)"
    },
    {
      "text": "▲ 기후부, 우기 대비 전력망 건설 현장점검(09:30 함안)"
    },
    {
      "text": "▲ 문체부, 한국배구연맹 총재 이·취임식(11:00 그랜드하얏트 서울)"
    },
    {
      "text": "▲ 미국 독립기념일 범선 행진 (미동부시간 13:00 뉴욕 이스트강)"
    },
    {
      "text": "▲ 중국 외교부 브리핑(16:00)"
    },
    {
      "text": "▲ 일본 외무상 정례 기자회견(16:15)"
    },
    {
      "text": "▲ 구윤철 부총리 겸 재정경제부 장관"
    },
    {
      "text": "08:30 비상경제본부 회의 겸 경제관계장관회의(정부세종청사)"
    },
    {
      "text": "07:45 차관회의(정부서울청사)"
    },
    {
      "text": "07:45 차관회의"
    },
    {
      "text": "08:30 비상경제본부회의 겸 경제관계장관회의(정부서울청사)"
    },
    {
      "text": "10:00 성균관대 실험실창업 현장방문(수원 성균관대 창업보육센터)"
    },
    {
      "text": "09:30 글로벌AI 프론티어 심포지엄(웨스틴 서울 파르나스)"
    },
    {
      "text": "14:00 연구데이터 생산활용 현장방문(KIST)"
    },
    {
      "text": "7:45 차관회의(정부세종청사)"
    },
    {
      "text": "07:45 차관회의(서울)"
    },
    {
      "text": "13:20 신선식품 배송서비스 출범식(경북 의성)"
    },
    {
      "text": "14:05 지방소멸대응기금 현장방문(경북 의성)"
    },
    {
      "text": "14:30 배송현장 사무소 및 마을 방문(경북 의성)"
    },
    {
      "text": "▲ 권오을 장관"
    },
    {
      "text": "15:10 당정협의(드래곤시티호텔)"
    },
    {
      "text": "11:00 한국배구연맹 총재 이·취임식(그랜드하얏트 서울)"
    },
    {
      "text": "▲ 송미령 장관"
    },
    {
      "text": "09:00 여름철 재해 대비 추진상황 점검회의 개최(세종)"
    },
    {
      "text": "10:00 국정과제 및 현안점검회의(세종)"
    },
    {
      "text": "10:00 차관회의(잠정)(세종)"
    },
    {
      "text": "08:30 비상경제본부회의 겸 경제관계장관회의 개최계획(정부서울청사)"
    },
    {
      "text": "08:00 국립의학전문대학원 설립준비위원회(프레스센터)"
    },
    {
      "text": "[기후에너지환경부]"
    },
    {
      "text": "▲ 김성환 장관"
    },
    {
      "text": "10:00 비닐봉투 없는 날 1회용품 감량 캠페인(서울)"
    },
    {
      "text": "09:30 우기 대비 전력망 건설 현장점검(함안)"
    },
    {
      "text": "▲ 김영훈 장관"
    },
    {
      "text": "14:00 제조업 동일 유형 반복 산재 사고 예방 점검 회의(서울)"
    },
    {
      "text": "15:00 제2차 고용노동부 양성평등위원회(서울)"
    },
    {
      "text": "▲ 원민경 장관"
    },
    {
      "text": "14:00 경찰-가정폭력상담소 공동대응체계 현장간담회(정부서울청사)"
    },
    {
      "text": "▲ 김윤덕 장관"
    },
    {
      "text": "09:30 집중호우 대비 현장점검(신탄진)"
    },
    {
      "text": "08:30 비상경제본부 회의(정부서울청사)"
    },
    {
      "text": "[금융위원회]"
    },
    {
      "text": "09:10 벤처생태계 간담회(부산 유라시아플랫폼)"
    },
    {
      "text": "10:50 서민금융복합 지원센터 개소식(부산 서민금융 복합지원센터)"
    },
    {
      "text": "■ 국회"
    },
    {
      "text": "▲ 국회의장"
    },
    {
      "text": "정은경 보건복지부 장관 접견 (14:00 의장 집무실)"
    },
    {
      "text": "▲ 위원회"
    },
    {
      "text": "재정경제기획위원회 전체회의 (11:00 본관 430호)"
    },
    {
      "text": "김주영 의원실 등, (통합적인 기후변화 감시·예측·영향정보 기반의) 국가 기후위기 대응체계 강화 전략 토론회 (10:00 의원회관 제3세미나실)"
    },
    {
      "text": "오세희 의원실 등, AI 시대, 여성 기술창업 활성화를 위한 구조적 전환 정책토론회 (10:00 의원회관 제1소회의실)"
    },
    {
      "text": "김용태 의원실 등, K-캠핑 육성과 외국인 관광객 3천만명 시대 캠핑관광 활성화를 위한 세미나 (10:00 의원회관 제2소회의실)"
    },
    {
      "text": "성일종 의원실 등, 반도체 대한민국 국방·외교·안보 전략자산 (10:00 의원회관 제2세미나실)"
    },
    {
      "text": "서미화 의원실 등, 아동·청소년의 집은 어디에 있는가 (10:00 의원회관 제10간담회의실)"
    },
    {
      "text": "송영길 의원실 등, 평화·외교·안보 분야 평가와 과제: 이재명 정부 1년 (10:00 의원회관 제9간담회의실)"
    },
    {
      "text": "신장식 의원실 등, 자유인·문화인·평화인 노회찬: 민주주의 위기의 시대 vs 노회찬의 민주주의 (14:00 의원회관 제3세미나실)"
    },
    {
      "text": "조배숙 의원, 호남 반도체 클러스터 관련 기자회견 (09:20)"
    },
    {
      "text": "유용원 의원, 현안 관련 기자회견 (10:00)"
    },
    {
      "text": "모경종 의원, 정년연장 관련 청년 국회의원 기자회견 (10:20)"
    },
    {
      "text": "정혜경 의원, 쿠팡 CLS 프레시백 공짜노동 중단과 보복성 집단해고 철회 촉구 기자회견 (10:40)"
    },
    {
      "text": "김민전 의원, 정치 현안 관련 기자회견 (11:00)"
    },
    {
      "text": "모경종 의원, 김형남 전 서울시장 경선후보, 더불어민주당 최고위원 출마선언 기자회견 (11:20)"
    },
    {
      "text": "이성윤 의원, 주요 현안 관련 기자회견 (11:40)"
    },
    {
      "text": "김현 의원, 더불어민주당 국민소통위원회 민주파출소 정례브리핑 (13:40)"
    },
    {
      "text": "14:30 공항동 연합상권 민생현장방문(강서구 공항동 먹자골목 등)"
    },
    {
      "text": "09:10 부산 벤처생태계 활성화 간담회(부산유라시아플랫폼)"
    },
    {
      "text": "10:50 부산 서민금융 복합지원센터 개소식(부산서민금융복합지원센터)"
    },
    {
      "text": "10:30 광주 재해침수지역 점검(북구 신안동)"
    },
    {
      "text": "10:30 2026메디엑스포코리아 개막식(엑스코 동관)"
    },
    {
      "text": "10:00 7월 월간회의(2층 대회의실)"
    },
    {
      "text": "11:00 제5대 세종시의회 개원식(시의회 본회의장)"
    },
    {
      "text": "14:00 2026 한글문화콘텐츠산업 워크숍(책문화센터(4층))"
    },
    {
      "text": "10:30 신임의장단 접견(도지사실)"
    },
    {
      "text": "13:05 언론사 방문(청주)"
    },
    {
      "text": "11:00 A사 업무협약식(구미시청)"
    },
    {
      "text": "17:30 2026 경북 글로벌 차세대 리더스 커넥트 토론회 환영 만찬(스탠포드호텔 안동)"
    },
    {
      "text": "▲ 부산 서민금융 복합지원센터 개소식(10:30 부산서민융복합지원센터)"
    },
    {
      "text": "▲ 2026년 부산 중소기업인 대회(15:00 웨스틴 조선)"
    },
    {
      "text": "▲ 국내·외 대상 함안낙화페스티벌(16:00 함안 무진정 일원)"
    },
    {
      "text": "▲ 전남광주통합의회 2차 본회의(10:00 전남도의회청사)"
    },
    {
      "text": "▲ 중국 산둥성 칭다오시장 제주 방문(09:00 백록홀)"
    }
  ],
  "raw_text": "▲ 장인화 포스코그룹 회장이 2일 서울 콘래드 호텔에서 열린 'CEO 인베스터데이'에서 그룹의 새로운 미래 성장 전략을 발표하고 있다. ⓒ 연합뉴스\n■ 분야별\n[정치]\n▲ 한성숙 국무총리, 홍수 대응체계 현장점검(11:00 서초구)\n, 후반기 국회 대비 국회의원 워크숍(14:00 용산구)\n▲ 조정식 국회의장, 정은경 보건복지부 장관 접견(14:00 의장 집무실)\n▲ 국회 재정경제기획위원회 전체회의(11:00 본관 430호)\n▲ 더불어민주당\n한병도 당대표 직무대행 및 원내대표, 최고위원회의(09:30 본관 당대표회의실)\n한병도 당대표 직무대행 및 원내대표, 후반기 국회 대비 국회의원 워크숍(14:00 서울드래곤시티호텔)\n정점식 원내대표, 원내대책회의(09:00 본관 245호)\n▲ 조국혁신당\n신장식 당대표 권한대행, 소상공인연합회 정책간담회(10:00 소상공인연합회)\n신장식 당대표 권한대행, 노회찬 8주기 추모 행사(14:00 국회의원회관 제3세미나실)\n김준형 원내대표, 유튜브 <장르만 여의도> 출연(12:00)\n다른 내일 아카데미 특강(19:00 부평아트센터)\n▲ 개혁신당\n이준석 대표, 메타콘 2026(10:00 코엑스 그랜드볼룸)\n이준석 대표, 재정경제기획위원회 전체회의(11:00 본관 430호)\n이준석 대표, 2026년 장애인 인권 증진 토론회(14:00 국회도서관 대강당)\n[외교안보]\n▲ 보훈부, 당정협의(15:10 드래곤시티호텔)\n[경제]\n▲ 금융위, 벤처생태계 간담회(09:10 부산 유라시아플랫폼)\n▲ 금융위, 서민금융복합 지원센터 개소식(10:50 부산 서민금융 복합지원센터)\n▲ 재경부, 비상경제본부 회의 겸 경제관계장관회의(08:30 정부세종청사)\n▲ 기획처, 비상경제본부회의 겸 경제관계장관회의(08:30 정부서울청사)\n[산업]\n▲ 산업부, 비상경제본부회의 겸 경제관계장관회의 개최계획(08:30 정부서울청사)\n▲ 국토부, 집중호우 대비 현장점검(09:30 신탄진)\n[소비자경제]\n▲ 농식품부, 여름철 재해 대비 추진상황 점검회의 개최(09:00 세종)\n▲ 농식품부, 국정과제 및 현안점검회의(10:00 세종)\n▲ 중기부, 비상경제본부 회의(08:30 정부서울청사)\n[테크]\n▲ 과기부, 글로벌AI 프론티어 심포지엄(09:30 웨스틴 서울 파르나스)\n▲ 과기부, 성균관대 실험실창업 현장방문(10:00 수원 성균관대 창업보육센터)\n▲ 과기부, 연구데이터 생산활용 현장방문(14:00 KIST)\n[사회]\n▲ 오세훈 서울시장, 공항동 연합상권 민생현장방문(14:30 강서구 공항동 먹자골목 등)\n[정책사회]\n▲ 행안부, 신선식품 배송서비스 출범식(13:20 경북 의성)\n▲ 행안부, 지방소멸대응기금 현장방문(14:05 경북 의성)\n▲ 행안부, 배송현장 사무소 및 마을 방문(14:30 경북 의성)\n▲ 이정렬 개보위 부위원장, 개인정보 현장 컨설팅(14:00 대전정보문화산업진흥원)\n▲ 성평등부, 경찰-가정폭력상담소 공동대응체계 현장간담회(14:00 정부서울청사)\n▲ 복지부, 국립의학전문대학원 설립준비위원회(08:00 프레스센터)\n▲ 노동부, 제조업 동일 유형 반복 산재 사고 예방 점검 회의(14:00 서울)\n▲ 노동부, 제2차 고용노동부 양성평등위원회(15:00 서울)\n▲ 기후부, 비닐봉투 없는 날 1회용품 감량 캠페인(10:00 서울)\n▲ 기후부, 우기 대비 전력망 건설 현장점검(09:30 함안)\n[문화]\n▲ 문체부, 한국배구연맹 총재 이·취임식(11:00 그랜드하얏트 서울)\n[국제](현지시간)\n▲ 미국 독립기념일 범선 행진 (미동부시간 13:00 뉴욕 이스트강)\n▲ 독일·발트3국 정상 회동(독일 베를린)\n▲ 중국 외교부 브리핑(16:00)\n▲ 일본 외무상 정례 기자회견(16:15)\n■ 총리 및 장차관\n[재경부]\n▲ 구윤철 부총리 겸 재정경제부 장관\n08:30 비상경제본부 회의 겸 경제관계장관회의(정부세종청사)\n▲ 허장 2차관\n07:45 차관회의(정부서울청사)\n[기획처]\n▲ 임기근 기획예산처 차관\n07:45 차관회의\n08:30 비상경제본부회의 겸 경제관계장관회의(정부서울청사)\n[과기정통부]\n▲ 구혁채 1차관\n10:00 성균관대 실험실창업 현장방문(수원 성균관대 창업보육센터)\n▲ 류제명 2차관\n09:30 글로벌AI 프론티어 심포지엄(웨스틴 서울 파르나스)\n▲ 박인규 혁신본부장\n14:00 연구데이터 생산활용 현장방문(KIST)\n[교육부]\n▲ 최은옥 차관\n7:45 차관회의(정부세종청사)\n[외교부]\n▲ 박윤주 1차관\n07:45 차관회의\n[국방부]\n▲ 이두희 차관\n07:45 차관회의\n[행안부]\n▲ 김민재 차관\n07:45 차관회의(서울)\n13:20 신선식품 배송서비스 출범식(경북 의성)\n14:05 지방소멸대응기금 현장방문(경북 의성)\n14:30 배송현장 사무소 및 마을 방문(경북 의성)\n[보훈부]\n▲ 권오을 장관\n15:10 당정협의(드래곤시티호텔)\n[문체부]\n▲ 김대현 2차관\n11:00 한국배구연맹 총재 이·취임식(그랜드하얏트 서울)\n[농식품부]\n▲ 송미령 장관\n09:00 여름철 재해 대비 추진상황 점검회의 개최(세종)\n10:00 국정과제 및 현안점검회의(세종)\n▲ 김종구 차관\n10:00 차관회의(잠정)(세종)\n[산업통상부]\n▲ 문신학 1차관\n08:30 비상경제본부회의 겸 경제관계장관회의 개최계획(정부서울청사)\n[복지부]\n▲ 이형훈 2차관\n08:00 국립의학전문대학원 설립준비위원회(프레스센터)\n[기후에너지환경부]\n▲ 김성환 장관\n10:00 비닐봉투 없는 날 1회용품 감량 캠페인(서울)\n▲ 이호현 2차관\n09:30 우기 대비 전력망 건설 현장점검(함안)\n[노동부]\n▲ 김영훈 장관\n14:00 제조업 동일 유형 반복 산재 사고 예방 점검 회의(서울)\n▲ 권창준 차관\n07:45 차관회의(정부서울청사)\n15:00 제2차 고용노동부 양성평등위원회(서울)\n[성평등가족부]\n▲ 원민경 장관\n14:00 경찰-가정폭력상담소 공동대응체계 현장간담회(정부서울청사)\n▲ 정구창 차관\n07:45 차관회의(정부서울청사)\n[국토부]\n▲ 김윤덕 장관\n09:30 집중호우 대비 현장점검(신탄진)\n[중소벤처기업부]\n▲ 이병권 2차관\n07:45 차관회의(정부서울청사)\n08:30 비상경제본부 회의(정부서울청사)\n[금융위원회]\n▲ 이억원 위원장\n09:10 벤처생태계 간담회(부산 유라시아플랫폼)\n10:50 서민금융복합 지원센터 개소식(부산 서민금융 복합지원센터)\n■ 국회\n▲ 국회의장\n정은경 보건복지부 장관 접견 (14:00 의장 집무실)\n▲ 위원회\n재정경제기획위원회 전체회의 (11:00 본관 430호)\n▲ 의원실 세미나\n김주영 의원실 등, (통합적인 기후변화 감시·예측·영향정보 기반의) 국가 기후위기 대응체계 강화 전략 토론회 (10:00 의원회관 제3세미나실)\n오세희 의원실 등, AI 시대, 여성 기술창업 활성화를 위한 구조적 전환 정책토론회 (10:00 의원회관 제1소회의실)\n김용태 의원실 등, K-캠핑 육성과 외국인 관광객 3천만명 시대 캠핑관광 활성화를 위한 세미나 (10:00 의원회관 제2소회의실)\n성일종 의원실 등, 반도체 대한민국 국방·외교·안보 전략자산 (10:00 의원회관 제2세미나실)\n서미화 의원실 등, 아동·청소년의 집은 어디에 있는가 (10:00 의원회관 제10간담회의실)\n송영길 의원실 등, 평화·외교·안보 분야 평가와 과제: 이재명 정부 1년 (10:00 의원회관 제9간담회의실)\n신장식 의원실 등, 자유인·문화인·평화인 노회찬: 민주주의 위기의 시대 vs 노회찬의 민주주의 (14:00 의원회관 제3세미나실)\n▲ 소통관 기자회견\n조배숙 의원, 호남 반도체 클러스터 관련 기자회견 (09:20)\n유용원 의원, 현안 관련 기자회견 (10:00)\n모경종 의원, 정년연장 관련 청년 국회의원 기자회견 (10:20)\n정혜경 의원, 쿠팡 CLS 프레시백 공짜노동 중단과 보복성 집단해고 철회 촉구 기자회견 (10:40)\n김민전 의원, 정치 현안 관련 기자회견 (11:00)\n모경종 의원, 김형남 전 서울시장 경선후보, 더불어민주당 최고위원 출마선언 기자회견 (11:20)\n이성윤 의원, 주요 현안 관련 기자회견 (11:40)\n김현 의원, 더불어민주당 국민소통위원회 민주파출소 정례브리핑 (13:40)\n■ 시도지사\n▲ 오세훈 서울시장\n14:30 공항동 연합상권 민생현장방문(강서구 공항동 먹자골목 등)\n▲ 전재수 부산시장\n09:10 부산 벤처생태계 활성화 간담회(부산유라시아플랫폼)\n10:50 부산 서민금융 복합지원센터 개소식(부산서민금융복합지원센터)\n▲ 민형배 전남광주통합특별시장\n10:30 광주 재해침수지역 점검(북구 신안동)\n▲ 추경호 대구시장\n10:30 2026메디엑스포코리아 개막식(엑스코 동관)\n▲ 김상욱 울산시장\n10:00 7월 월간회의(2층 대회의실)\n▲ 조상호 세종시장\n11:00 제5대 세종시의회 개원식(시의회 본회의장)\n14:00 2026 한글문화콘텐츠산업 워크숍(책문화센터(4층))\n▲ 신용한 충북지사\n10:30 신임의장단 접견(도지사실)\n13:05 언론사 방문(청주)\n▲ 이철우 경북지사\n11:00 A사 업무협약식(구미시청)\n17:30 2026 경북 글로벌 차세대 리더스 커넥트 토론회 환영 만찬(스탠포드호텔 안동)\n[부산]\n▲ 부산 서민금융 복합지원센터 개소식(10:30 부산서민융복합지원센터)\n▲ 2026년 부산 중소기업인 대회(15:00 웨스틴 조선)\n[경남]\n▲ 국내·외 대상 함안낙화페스티벌(16:00 함안 무진정 일원)\n[광주전남]\n▲ 전남광주통합의회 2차 본회의(10:00 전남도의회청사)\n[제주]\n▲ 중국 산둥성 칭다오시장 제주 방문(09:00 백록홀)\n■ 스포츠\n▲ 프로야구= 한화-LG(잠실) 삼성-SSG(인천) NC-KIA(광주) 롯데-kt(수원) 두산-키움(고척·이상 18시30분)\n▲ 농구= FIBA 월드컵 아시아 예선 한국-대만(19시30분·고양 소노 아레나)\n▲ 골프= KLPGA 투어 제16회 롯데오픈(베어즈베스트 청라)\n▲ 테니스= 하나증권 제5회 협회장배 전국대회(10시·강원 양구 테니스파크)\n▲ 씨름= 제40회 전국시·도대항장사대회(10시·경남 창녕국민체육센터)\n▲ 체조= 제51회 KBS배 전국기계체조대회(10시·강원 홍천종합체육관)\n▲ 펜싱= 전국남녀종별선수권대회(9시·제천 세명대 체육관 등)\n[알림] 오늘의 일정 게재나 수정이 필요한 기관(단체)는 편집기획팀 전화(☎ 02-953-0119) 또는 이메일(safebodo@gmail.com)으로 보내 주시길 바랍니다.",
  "body": "▲ 장인화 포스코그룹 회장이 2일 서울 콘래드 호텔에서 열린 'CEO 인베스터데이'에서 그룹의 새로운 미래 성장 전략을 발표하고 있다. ⓒ 연합뉴스\n■ 분야별\n[정치]\n▲ 한성숙 국무총리, 홍수 대응체계 현장점검(11:00 서초구)\n, 후반기 국회 대비 국회의원 워크숍(14:00 용산구)\n▲ 조정식 국회의장, 정은경 보건복지부 장관 접견(14:00 의장 집무실)\n▲ 국회 재정경제기획위원회 전체회의(11:00 본관 430호)\n▲ 더불어민주당\n한병도 당대표 직무대행 및 원내대표, 최고위원회의(09:30 본관 당대표회의실)\n한병도 당대표 직무대행 및 원내대표, 후반기 국회 대비 국회의원 워크숍(14:00 서울드래곤시티호텔)\n정점식 원내대표, 원내대책회의(09:00 본관 245호)\n▲ 조국혁신당\n신장식 당대표 권한대행, 소상공인연합회 정책간담회(10:00 소상공인연합회)\n신장식 당대표 권한대행, 노회찬 8주기 추모 행사(14:00 국회의원회관 제3세미나실)\n김준형 원내대표, 유튜브 <장르만 여의도> 출연(12:00)\n다른 내일 아카데미 특강(19:00 부평아트센터)\n▲ 개혁신당\n이준석 대표, 메타콘 2026(10:00 코엑스 그랜드볼룸)\n이준석 대표, 재정경제기획위원회 전체회의(11:00 본관 430호)\n이준석 대표, 2026년 장애인 인권 증진 토론회(14:00 국회도서관 대강당)\n[외교안보]\n▲ 보훈부, 당정협의(15:10 드래곤시티호텔)\n[경제]\n▲ 금융위, 벤처생태계 간담회(09:10 부산 유라시아플랫폼)\n▲ 금융위, 서민금융복합 지원센터 개소식(10:50 부산 서민금융 복합지원센터)\n▲ 재경부, 비상경제본부 회의 겸 경제관계장관회의(08:30 정부세종청사)\n▲ 기획처, 비상경제본부회의 겸 경제관계장관회의(08:30 정부서울청사)\n[산업]\n▲ 산업부, 비상경제본부회의 겸 경제관계장관회의 개최계획(08:30 정부서울청사)\n▲ 국토부, 집중호우 대비 현장점검(09:30 신탄진)\n[소비자경제]\n▲ 농식품부, 여름철 재해 대비 추진상황 점검회의 개최(09:00 세종)\n▲ 농식품부, 국정과제 및 현안점검회의(10:00 세종)\n▲ 중기부, 비상경제본부 회의(08:30 정부서울청사)\n[테크]\n▲ 과기부, 글로벌AI 프론티어 심포지엄(09:30 웨스틴 서울 파르나스)\n▲ 과기부, 성균관대 실험실창업 현장방문(10:00 수원 성균관대 창업보육센터)\n▲ 과기부, 연구데이터 생산활용 현장방문(14:00 KIST)\n[사회]\n▲ 오세훈 서울시장, 공항동 연합상권 민생현장방문(14:30 강서구 공항동 먹자골목 등)\n[정책사회]\n▲ 행안부, 신선식품 배송서비스 출범식(13:20 경북 의성)\n▲ 행안부, 지방소멸대응기금 현장방문(14:05 경북 의성)\n▲ 행안부, 배송현장 사무소 및 마을 방문(14:30 경북 의성)\n▲ 이정렬 개보위 부위원장, 개인정보 현장 컨설팅(14:00 대전정보문화산업진흥원)\n▲ 성평등부, 경찰-가정폭력상담소 공동대응체계 현장간담회(14:00 정부서울청사)\n▲ 복지부, 국립의학전문대학원 설립준비위원회(08:00 프레스센터)\n▲ 노동부, 제조업 동일 유형 반복 산재 사고 예방 점검 회의(14:00 서울)\n▲ 노동부, 제2차 고용노동부 양성평등위원회(15:00 서울)\n▲ 기후부, 비닐봉투 없는 날 1회용품 감량 캠페인(10:00 서울)\n▲ 기후부, 우기 대비 전력망 건설 현장점검(09:30 함안)\n[문화]\n▲ 문체부, 한국배구연맹 총재 이·취임식(11:00 그랜드하얏트 서울)\n[국제](현지시간)\n▲ 미국 독립기념일 범선 행진 (미동부시간 13:00 뉴욕 이스트강)\n▲ 독일·발트3국 정상 회동(독일 베를린)\n▲ 중국 외교부 브리핑(16:00)\n▲ 일본 외무상 정례 기자회견(16:15)\n■ 총리 및 장차관\n[재경부]\n▲ 구윤철 부총리 겸 재정경제부 장관\n08:30 비상경제본부 회의 겸 경제관계장관회의(정부세종청사)\n▲ 허장 2차관\n07:45 차관회의(정부서울청사)\n[기획처]\n▲ 임기근 기획예산처 차관\n07:45 차관회의\n08:30 비상경제본부회의 겸 경제관계장관회의(정부서울청사)\n[과기정통부]\n▲ 구혁채 1차관\n10:00 성균관대 실험실창업 현장방문(수원 성균관대 창업보육센터)\n▲ 류제명 2차관\n09:30 글로벌AI 프론티어 심포지엄(웨스틴 서울 파르나스)\n▲ 박인규 혁신본부장\n14:00 연구데이터 생산활용 현장방문(KIST)\n[교육부]\n▲ 최은옥 차관\n7:45 차관회의(정부세종청사)\n[외교부]\n▲ 박윤주 1차관\n07:45 차관회의\n[국방부]\n▲ 이두희 차관\n07:45 차관회의\n[행안부]\n▲ 김민재 차관\n07:45 차관회의(서울)\n13:20 신선식품 배송서비스 출범식(경북 의성)\n14:05 지방소멸대응기금 현장방문(경북 의성)\n14:30 배송현장 사무소 및 마을 방문(경북 의성)\n[보훈부]\n▲ 권오을 장관\n15:10 당정협의(드래곤시티호텔)\n[문체부]\n▲ 김대현 2차관\n11:00 한국배구연맹 총재 이·취임식(그랜드하얏트 서울)\n[농식품부]\n▲ 송미령 장관\n09:00 여름철 재해 대비 추진상황 점검회의 개최(세종)\n10:00 국정과제 및 현안점검회의(세종)\n▲ 김종구 차관\n10:00 차관회의(잠정)(세종)\n[산업통상부]\n▲ 문신학 1차관\n08:30 비상경제본부회의 겸 경제관계장관회의 개최계획(정부서울청사)\n[복지부]\n▲ 이형훈 2차관\n08:00 국립의학전문대학원 설립준비위원회(프레스센터)\n[기후에너지환경부]\n▲ 김성환 장관\n10:00 비닐봉투 없는 날 1회용품 감량 캠페인(서울)\n▲ 이호현 2차관\n09:30 우기 대비 전력망 건설 현장점검(함안)\n[노동부]\n▲ 김영훈 장관\n14:00 제조업 동일 유형 반복 산재 사고 예방 점검 회의(서울)\n▲ 권창준 차관\n07:45 차관회의(정부서울청사)\n15:00 제2차 고용노동부 양성평등위원회(서울)\n[성평등가족부]\n▲ 원민경 장관\n14:00 경찰-가정폭력상담소 공동대응체계 현장간담회(정부서울청사)\n▲ 정구창 차관\n07:45 차관회의(정부서울청사)\n[국토부]\n▲ 김윤덕 장관\n09:30 집중호우 대비 현장점검(신탄진)\n[중소벤처기업부]\n▲ 이병권 2차관\n07:45 차관회의(정부서울청사)\n08:30 비상경제본부 회의(정부서울청사)\n[금융위원회]\n▲ 이억원 위원장\n09:10 벤처생태계 간담회(부산 유라시아플랫폼)\n10:50 서민금융복합 지원센터 개소식(부산 서민금융 복합지원센터)\n■ 국회\n▲ 국회의장\n정은경 보건복지부 장관 접견 (14:00 의장 집무실)\n▲ 위원회\n재정경제기획위원회 전체회의 (11:00 본관 430호)\n▲ 의원실 세미나\n김주영 의원실 등, (통합적인 기후변화 감시·예측·영향정보 기반의) 국가 기후위기 대응체계 강화 전략 토론회 (10:00 의원회관 제3세미나실)\n오세희 의원실 등, AI 시대, 여성 기술창업 활성화를 위한 구조적 전환 정책토론회 (10:00 의원회관 제1소회의실)\n김용태 의원실 등, K-캠핑 육성과 외국인 관광객 3천만명 시대 캠핑관광 활성화를 위한 세미나 (10:00 의원회관 제2소회의실)\n성일종 의원실 등, 반도체 대한민국 국방·외교·안보 전략자산 (10:00 의원회관 제2세미나실)\n서미화 의원실 등, 아동·청소년의 집은 어디에 있는가 (10:00 의원회관 제10간담회의실)\n송영길 의원실 등, 평화·외교·안보 분야 평가와 과제: 이재명 정부 1년 (10:00 의원회관 제9간담회의실)\n신장식 의원실 등, 자유인·문화인·평화인 노회찬: 민주주의 위기의 시대 vs 노회찬의 민주주의 (14:00 의원회관 제3세미나실)\n▲ 소통관 기자회견\n조배숙 의원, 호남 반도체 클러스터 관련 기자회견 (09:20)\n유용원 의원, 현안 관련 기자회견 (10:00)\n모경종 의원, 정년연장 관련 청년 국회의원 기자회견 (10:20)\n정혜경 의원, 쿠팡 CLS 프레시백 공짜노동 중단과 보복성 집단해고 철회 촉구 기자회견 (10:40)\n김민전 의원, 정치 현안 관련 기자회견 (11:00)\n모경종 의원, 김형남 전 서울시장 경선후보, 더불어민주당 최고위원 출마선언 기자회견 (11:20)\n이성윤 의원, 주요 현안 관련 기자회견 (11:40)\n김현 의원, 더불어민주당 국민소통위원회 민주파출소 정례브리핑 (13:40)\n■ 시도지사\n▲ 오세훈 서울시장\n14:30 공항동 연합상권 민생현장방문(강서구 공항동 먹자골목 등)\n▲ 전재수 부산시장\n09:10 부산 벤처생태계 활성화 간담회(부산유라시아플랫폼)\n10:50 부산 서민금융 복합지원센터 개소식(부산서민금융복합지원센터)\n▲ 민형배 전남광주통합특별시장\n10:30 광주 재해침수지역 점검(북구 신안동)\n▲ 추경호 대구시장\n10:30 2026메디엑스포코리아 개막식(엑스코 동관)\n▲ 김상욱 울산시장\n10:00 7월 월간회의(2층 대회의실)\n▲ 조상호 세종시장\n11:00 제5대 세종시의회 개원식(시의회 본회의장)\n14:00 2026 한글문화콘텐츠산업 워크숍(책문화센터(4층))\n▲ 신용한 충북지사\n10:30 신임의장단 접견(도지사실)\n13:05 언론사 방문(청주)\n▲ 이철우 경북지사\n11:00 A사 업무협약식(구미시청)\n17:30 2026 경북 글로벌 차세대 리더스 커넥트 토론회 환영 만찬(스탠포드호텔 안동)\n[부산]\n▲ 부산 서민금융 복합지원센터 개소식(10:30 부산서민융복합지원센터)\n▲ 2026년 부산 중소기업인 대회(15:00 웨스틴 조선)\n[경남]\n▲ 국내·외 대상 함안낙화페스티벌(16:00 함안 무진정 일원)\n[광주전남]\n▲ 전남광주통합의회 2차 본회의(10:00 전남도의회청사)\n[제주]\n▲ 중국 산둥성 칭다오시장 제주 방문(09:00 백록홀)\n■ 스포츠\n▲ 프로야구= 한화-LG(잠실) 삼성-SSG(인천) NC-KIA(광주) 롯데-kt(수원) 두산-키움(고척·이상 18시30분)\n▲ 농구= FIBA 월드컵 아시아 예선 한국-대만(19시30분·고양 소노 아레나)\n▲ 골프= KLPGA 투어 제16회 롯데오픈(베어즈베스트 청라)\n▲ 테니스= 하나증권 제5회 협회장배 전국대회(10시·강원 양구 테니스파크)\n▲ 씨름= 제40회 전국시·도대항장사대회(10시·경남 창녕국민체육센터)\n▲ 체조= 제51회 KBS배 전국기계체조대회(10시·강원 홍천종합체육관)\n▲ 펜싱= 전국남녀종별선수권대회(9시·제천 세명대 체육관 등)\n[알림] 오늘의 일정 게재나 수정이 필요한 기관(단체)는 편집기획팀 전화(☎ 02-953-0119) 또는 이메일(safebodo@gmail.com)으로 보내 주시길 바랍니다.",
  "success": true,
  "quality": {
    "needs_review": true,
    "warnings": [
      "세이프타임즈 기사 본문을 자동 파싱한 초안입니다.",
      "기사 원문 기준 일정은 사실 데이터이며, 정유/석화/LNG 영향도는 후속 변환 단계의 해석입니다."
    ]
  }
}