{
  "schema_version": "2.6",
  "date": "2026-06-12",
  "report_slot": "morning",
  "collected_at": "2026-06-12 08:04:44 KST",
  "source": "Naver News Search HTML + Daum News Search HTML + Google News RSS",
  "queries": [
    "국제유가 OR 유가 OR 원유 OR 브렌트유 OR WTI OR 두바이유",
    "정유 OR 정유사 OR 석유제품 OR 주유소 OR 유류세 OR 휘발유 OR 경유",
    "석유화학 OR 나프타 OR 에틸렌 OR 프로필렌 OR 화학제품",
    "LNG OR 천연가스 OR 가스공사 OR 도시가스",
    "최고가격제 OR 가격상한 OR 유류세 OR 석탄및석유제품",
    "호르무즈 OR 원유 수급 OR 석유 공급망 OR OPEC",
    "산업부 석유 OR 공정위 석유 OR 국회 유류세",
    "생산자물가 석유제품 OR 소비자물가 유류세 OR 수입물가 원유",
    "전력 LNG OR 에너지 국제유가 OR 물가 석유제품",
    "경제 유가 OR 산업 에너지",
    "정부 유류세 OR 전력 LNG",
    "산업부 에너지 OR 기재부 물가 석유",
    "국제유가",
    "유가",
    "원유",
    "석유제품",
    "정유",
    "정유사",
    "주유소",
    "유류세",
    "휘발유",
    "경유",
    "석유화학",
    "나프타",
    "LNG",
    "천연가스",
    "최고가격제",
    "호르무즈",
    "전력 LNG",
    "에너지 국제유가",
    "물가 석유제품",
    "생산자물가 석유제품"
  ],
  "time_window": "2026-06-11 17:00~2026-06-12 08:00 KST",
  "summary": "△석유 최고가격제·유류세 등 가격 안정 정책 △중동 정세와 원유·LNG 수급 리스크 △정유·석유화학 업계 실적·원가·제품 가격 △물가 지표와 에너지 비용 부담",
  "topics": [
    "석유 최고가격제·유류세 등 가격 안정 정책",
    "중동 정세와 원유·LNG 수급 리스크",
    "정유·석유화학 업계 실적·원가·제품 가격",
    "물가 지표와 에너지 비용 부담"
  ],
  "articles": [
    {
      "title": "韓 LNG선 호르무즈 통과… 유조선 이어 두번째",
      "press": "동아일보",
      "press_grade": "A",
      "url": "https://v.daum.net/v/20260612043250292",
      "published_date": "2026-06-12",
      "published_at_kst": "",
      "snippet": "동아일보 개별문서메뉴 톡으로 바로 공유 공유하기 韓 LNG선 호르무즈 통과… 유조선 이어 두번째 이 선박은 최종 목적지인 제3국으로 향하고 있다”고 설명했다. 해수부에 따르면 해당 선박은 한국 선사가 운용하는 액화천연가스( LNG ) 운반선으로, 한국인 선원 8명이 승선하고 있다. 용선사는 카타르 국영기업인 ‘카타르에너지’로, 목적지는 한국이 아닌... 3시간 전",
      "score": 10,
      "score_breakdown": {
        "keyword": 5,
        "title_importance": 2,
        "press": 3,
        "originality": 0,
        "duplicate_or_low_quality": 0
      },
      "industry_relevance": 5,
      "source_query": "LNG",
      "collector": "daum_news_search"
    },
    {
      "title": "일, 대체 경로 확대로 7월 원유조달 전년 수준 회복",
      "press": "YTN",
      "press_grade": "B",
      "url": "https://v.daum.net/v/20260611173305790",
      "published_date": "2026-06-12",
      "published_at_kst": "",
      "snippet": "YTN 개별문서메뉴 톡으로 바로 공유 공유하기 일, 대체 경로 확대로 7월 원유조달 전년 수준 회복 일본 정부와 정유 업계가 오는 7월 확보하는 원유 물량이 지난해 같은 기간 수준을 완전히 회복할 전망이라고 교도통신이 보도했습니다. 통신에 따르면 다카이치 사나에 일본 총리는 오늘 저녁 열리는 중동 정세 대응 각료회의에서 이 같은 원유 조달 전망을 공식... 14시간 전",
      "score": 11,
      "score_breakdown": {
        "keyword": 5,
        "title_importance": 2,
        "press": 2,
        "originality": 2,
        "duplicate_or_low_quality": 0
      },
      "industry_relevance": 4,
      "source_query": "정유",
      "collector": "daum_news_search"
    },
    {
      "title": "\"종료시점 예단 힘들어\"…석유 최고가격제 출구전략 불투명",
      "press": "뉴시스",
      "press_grade": "A",
      "url": "https://v.daum.net/v/20260612050222773",
      "published_date": "2026-06-12",
      "published_at_kst": "",
      "snippet": "뉴시스 개별문서메뉴 톡으로 바로 공유 공유하기 3 \"종료시점 예단 힘들어\"…석유 최고가격제 출구전략 불투명 3월13일부터 급격한 유가 상승세를 억제하기 위해 석유 최고가격제를 시행했다. 중동 전쟁 발발 이후 유가가 폭등세를 나타내자 정유사 가 주유소에 공급하는 도매 가격에 최고가격을 설정한 것이다. 정부가 석유 가격에 상한선을 설정한 것은 1997년 유가 완전자유화... 3시간 전",
      "score": 13,
      "score_breakdown": {
        "keyword": 5,
        "title_importance": 4,
        "press": 3,
        "originality": 1,
        "duplicate_or_low_quality": 0
      },
      "industry_relevance": 4,
      "source_query": "정유사",
      "collector": "daum_news_search"
    },
    {
      "title": "전쟁중 ‘고가 나프타’ 역풍… 하반기 유화업계 실적 비상",
      "press": "동아일보",
      "press_grade": "A",
      "url": "https://v.daum.net/v/20260612003155795",
      "published_date": "2026-06-12",
      "published_at_kst": "",
      "snippet": "동아일보 언론사 픽 개별문서메뉴 톡으로 바로 공유 공유하기 2 전쟁중 ‘고가 나프타’ 역풍… 하반기 유화업계 실적 비상 전환 가능성이 크다는 게 업계 판단이다. 이에 정부와 업계가 추진 중인 석유 화학 구조조정을 통해 범용 제품 비중을 줄이고 고부가가치 제품 전환을 서둘러야 한다는 지적이 나온다. 석유 화학 구조조정 1호 사례인 대산 산단의 나프타분해설비(NCC) 통합 절차가... 7시간 전",
      "score": 11,
      "score_breakdown": {
        "keyword": 5,
        "title_importance": 2,
        "press": 3,
        "originality": 1,
        "duplicate_or_low_quality": 0
      },
      "industry_relevance": 4,
      "source_query": "석유제품",
      "collector": "daum_news_search"
    },
    {
      "title": "\"빠져나오나 했더니 원점\"…호르무즈 재봉쇄에 해운업계 '한숨'",
      "press": "뉴시스",
      "press_grade": "A",
      "url": "https://v.daum.net/v/20260612050152704",
      "published_date": "2026-06-12",
      "published_at_kst": "",
      "snippet": "뉴시스 개별문서메뉴 톡으로 바로 공유 공유하기 \"빠져나오나 했더니 원점\"…호르무즈 재봉쇄에 해운업계 '한숨' 모두 139명이다. 지난달 20일 초대형 원유운반선(VLCC) '유니버설 위너'호에 이어 지난 10일 한국 선사가 운항하는 액화천연가스( LNG ) 운반선 1척이 호르무즈 해협을 빠져나오면서, 해운업계에선 해협을 통과할 수 있을 것이란 기대감이 나오기도 했다. 다만 이란이... 3시간 전",
      "score": 11,
      "score_breakdown": {
        "keyword": 5,
        "title_importance": 2,
        "press": 3,
        "originality": 1,
        "duplicate_or_low_quality": 0
      },
      "industry_relevance": 4,
      "source_query": "LNG",
      "collector": "daum_news_search"
    },
    {
      "title": "호르무즈 길 열리나…트럼프 \"이번 주말\" 이란 \"아직\" 뉴욕증시는 '급등&apos...",
      "press": "이데일리",
      "press_grade": "A",
      "url": "https://v.daum.net/v/20260612075941661",
      "published_date": "2026-06-12",
      "published_at_kst": "",
      "snippet": "이데일리 개별문서메뉴 톡으로 바로 공유 공유하기 2 호르무즈 길 열리나…트럼프 \"이번 주말\" 이란 \"아직\" 뉴욕증시는 '급등&apos... 있어. 이란 외무부는 아직 최종 결정을 내리지 않았다고 밝혀 실제 종전 양해각서(MOU) 체결 여부가 주목돼. 종전 기대에 꺾인 국제 유가 -종전에 따른 호르무즈 해협 개방 기대로 국제 유가 는 이날 하락해. -8월 인도분 브렌트유 선물은 2.92% 내린 90.38달러를 기록... 4분 전",
      "score": 12,
      "score_breakdown": {
        "keyword": 5,
        "title_importance": 4,
        "press": 3,
        "originality": 0,
        "duplicate_or_low_quality": 0
      },
      "industry_relevance": 4,
      "source_query": "국제유가",
      "collector": "daum_news_search"
    },
    {
      "title": "\"호르무즈가 열린다... 유가 70달러까지 하락할 것\"",
      "press": "이데일리",
      "press_grade": "A",
      "url": "https://v.daum.net/v/20260612074649435",
      "published_date": "2026-06-12",
      "published_at_kst": "",
      "snippet": "이데일리 개별문서메뉴 톡으로 바로 공유 공유하기 \"호르무즈가 열린다... 유가 70달러까지 하락할 것\" 임박하면서 글로벌 금융시장의 최대 불안 요인이었던 호르무즈 해협 봉쇄가 풀릴 가능성이 높아졌다. 증권가에서는 해협 개방 시 국제 유가 가 70달러 초중반까지 하락하고 고물가·고금리·고달러의 3고 현상도 완화될 것으로 내다보고 있다. 호르무즈 해협에 면한... 17분 전",
      "score": 12,
      "score_breakdown": {
        "keyword": 5,
        "title_importance": 4,
        "press": 3,
        "originality": 0,
        "duplicate_or_low_quality": 0
      },
      "industry_relevance": 4,
      "source_query": "국제유가",
      "collector": "daum_news_search"
    },
    {
      "title": "\"삼성重, 상선 수주목표 90% 달성… LNG ·해양플랜트 호재 밀물\" iM증권",
      "press": "파이낸셜뉴스",
      "press_grade": "A",
      "url": "https://v.daum.net/v/20260612063038214",
      "published_date": "2026-06-12",
      "published_at_kst": "",
      "snippet": "파이낸셜뉴스 개별문서메뉴 톡으로 바로 공유 공유하기 \"삼성重, 상선 수주목표 90% 달성… LNG ·해양플랜트 호재 밀물\" iM증권 삼성중공업이 건조한 세계 최대 규모 크기의 FLNG. 삼성중공업 제공 [파이낸셜뉴스] 삼성중공업이 주력 선종인 액화천연가스( LNG ) 운반선의 압도적인 수주 잔고를 바탕으로 중장기 수익 기반을 확고히 다지고 있다. 여기에 부유식 액화천연가스 생산설비(FLNG) 등... 1시간 전",
      "score": 11,
      "score_breakdown": {
        "keyword": 5,
        "title_importance": 3,
        "press": 3,
        "originality": 0,
        "duplicate_or_low_quality": 0
      },
      "industry_relevance": 4,
      "source_query": "LNG",
      "collector": "daum_news_search"
    },
    {
      "title": "'러 LNG 제한' 유럽 합의 무색…\"1~5월 수입 작년보다 18% 증가\"",
      "press": "뉴스1",
      "press_grade": "A",
      "url": "https://v.daum.net/v/20260612003147789",
      "published_date": "2026-06-12",
      "published_at_kst": "",
      "snippet": "뉴스1 개별문서메뉴 톡으로 바로 공유 공유하기 '러 LNG 제한' 유럽 합의 무색…\"1~5월 수입 작년보다 18% 증가\" 스페인 바르셀로나 소재 액화천연가스( LNG ) 항만 터미널에 위치한 에나가스사(社)의 LNG 저장 탱크 ⓒ AFP=뉴스1 (서울=뉴스1) 유철종 전문위원 = 러시아산 가스 수입을 단계적으로 금지키로 한 유럽연합(EU)이 올해 1~5월 기간 중 러시아 북극 지역의 '야말... 7시간 전",
      "score": 11,
      "score_breakdown": {
        "keyword": 5,
        "title_importance": 3,
        "press": 3,
        "originality": 0,
        "duplicate_or_low_quality": 0
      },
      "industry_relevance": 4,
      "source_query": "LNG",
      "collector": "daum_news_search"
    },
    {
      "title": "원유 수출 1위 오른 美...달러 패권 넘어 에너지 패권",
      "press": "파이낸셜뉴스",
      "press_grade": "A",
      "url": "https://v.daum.net/v/20260612010948164",
      "published_date": "2026-06-12",
      "published_at_kst": "",
      "snippet": "파이낸셜뉴스 개별문서메뉴 톡으로 바로 공유 공유하기 원유 수출 1위 오른 美...달러 패권 넘어 에너지 패권 제치고 미국이 정상에 오른 것이다. 로이터통신은 11일(현지시간) 선박 추적업체 보텍사(Vortexa)를 인용해 미국의 원유 및 석유 제품 수출이 지난 5월 하루 평균 1050만배럴을 기록했다고 보도했다. 전략비축유 방출과 높은 생산량에 힘입어 미국은 3개월 연속 세계... 6시간 전 1",
      "score": 10,
      "score_breakdown": {
        "keyword": 5,
        "title_importance": 2,
        "press": 3,
        "originality": 0,
        "duplicate_or_low_quality": 0
      },
      "industry_relevance": 4,
      "source_query": "석유제품",
      "collector": "daum_news_search"
    },
    {
      "title": "호르무즈 막은 이란 “지옥 만들 것” [美-이란 전쟁]",
      "press": "서울경제",
      "press_grade": "A",
      "url": "https://v.daum.net/v/20260611174033064",
      "published_date": "2026-06-12",
      "published_at_kst": "",
      "snippet": "서울경제 개별문서메뉴 톡으로 바로 공유 공유하기 호르무즈 막은 이란 “지옥 만들 것” [美-이란 전쟁] 호르무즈해협 인근 케슘섬과 키시섬은 물론 수도 테헤란 서부에 위치한 알보르즈·카라지에서 폭발음이 감지됐으며 이란 최대 정유 시설인 아살루예 석유화학단지에서도 방공망이 가동됐다고 전했다. 미국은 8일과 9일·10일 연달아 호르무즈를 지나던 유조선을 공격... 14시간 전 5",
      "score": 10,
      "score_breakdown": {
        "keyword": 5,
        "title_importance": 2,
        "press": 3,
        "originality": 0,
        "duplicate_or_low_quality": 0
      },
      "industry_relevance": 4,
      "source_query": "정유",
      "collector": "daum_news_search"
    },
    {
      "title": "이란 남부 시리크에서 들린 폭음, 호르무즈 이란해군 대응 사격인 듯--이란 통신",
      "press": "뉴시스",
      "press_grade": "A",
      "url": "https://v.daum.net/v/20260612075341535",
      "published_date": "2026-06-12",
      "published_at_kst": "",
      "snippet": "뉴시스 언론사 픽 개별문서메뉴 톡으로 바로 공유 공유하기 이란 남부 시리크에서 들린 폭음, 호르무즈 이란해군 대응 사격인 듯--이란 통신 [코르 파칸(아랍에미리트)=AP/뉴시스]아랍에미리트(UAE) 코르 파칸 해안에서 1일 호르무즈 해협 봉쇄로 발이 묶인 유조선과 자동차운반선이 정박해 있는 모습이 보이고 있다. 이란의 반관영 타스님 통신은 6월 12일 새벽에 시리크 지역에서 들린 폭발음들이 반다르... 11분 전",
      "score": 8,
      "score_breakdown": {
        "keyword": 3,
        "title_importance": 2,
        "press": 3,
        "originality": 0,
        "duplicate_or_low_quality": 0
      },
      "industry_relevance": 4,
      "source_query": "호르무즈",
      "collector": "daum_news_search"
    }
  ],
  "errors": [],
  "success": true,
  "used_tier": "naver_html+daum_html"
}